README.rst
setup.py
patrol/__init__.py
patrol/reaper.py
patrol/task.py
patrol/trigger.py
patrol/watcher.py
patrol.egg-info/PKG-INFO
patrol.egg-info/SOURCES.txt
patrol.egg-info/dependency_links.txt
patrol.egg-info/not-zip-safe
patrol.egg-info/requires.txt
patrol.egg-info/top_level.txt
tests/__init__.py
tests/patrol1.py
tests/test_patrol.py