Metadata-Version: 1.1
Name: patrol
Version: 0.3.1
Summary: Trigger custom commands from filesystem events.
Home-page: https://github.com/crdoconnor/patrol
Author: Colm O'Connor
Author-email: colm.oconnor.github@gmail.com
License: MIT
Keywords: development environment tool pyuv epoll build
Platform: UNKNOWN
Classifier: Development Status :: 3 - Alpha
Classifier: Intended Audience :: Developers
Classifier: License :: OSI Approved :: MIT License
Classifier: Topic :: Software Development :: Build Tools
Classifier: Programming Language :: Python :: 2
Classifier: Programming Language :: Python :: 2.6
Classifier: Programming Language :: Python :: 2.7
Classifier: Programming Language :: Python :: 3
Classifier: Programming Language :: Python :: 3.1
Classifier: Programming Language :: Python :: 3.2
Classifier: Programming Language :: Python :: 3.3
